BeFake/BeFake.py
BeFake/__init__.py
BeFake/__main__.py
BeFake/utils.py
BeFake/models/__init__.py
BeFake/models/memory.py
BeFake/models/picture.py
BeFake/models/post.py
BeFake/models/realmoji.py
BeFake/models/realmoji_picture.py
BeFake/models/user.py
BeFake-1.0.0.dist-info/LICENSE
BeFake-1.0.0.dist-info/METADATA
BeFake-1.0.0.dist-info/WHEEL
BeFake-1.0.0.dist-info/entry_points.txt
BeFake-1.0.0.dist-info/top_level.txt
BeFake-1.0.0.dist-info/RECORD
